CHANGES.rst
CONTRIBUTORS.rst
MANIFEST.in
README.rst
base.cfg
bootstrap-buildout.py
buildout.cfg
plone-5.0.x.cfg
plone-5.1.x.cfg
setup.cfg
setup.py
test_plone51.cfg
test_plone52.cfg
versions.cfg
docs/LICENSE.GPL
docs/LICENSE.rst
docs/index.rst
src/collective/__init__.py
src/collective.outputfilters.enhancelinks.egg-info/PKG-INFO
src/collective.outputfilters.enhancelinks.egg-info/SOURCES.txt
src/collective.outputfilters.enhancelinks.egg-info/dependency_links.txt
src/collective.outputfilters.enhancelinks.egg-info/entry_points.txt
src/collective.outputfilters.enhancelinks.egg-info/namespace_packages.txt
src/collective.outputfilters.enhancelinks.egg-info/not-zip-safe
src/collective.outputfilters.enhancelinks.egg-info/requires.txt
src/collective.outputfilters.enhancelinks.egg-info/top_level.txt
src/collective/outputfilters/__init__.py
src/collective/outputfilters/enhancelinks/__init__.py
src/collective/outputfilters/enhancelinks/adapters.py
src/collective/outputfilters/enhancelinks/configure.zcml
src/collective/outputfilters/enhancelinks/enhance_links.py
src/collective/outputfilters/enhancelinks/interfaces.py
src/collective/outputfilters/enhancelinks/testing.py
src/collective/outputfilters/enhancelinks/tests/__init__.py
src/collective/outputfilters/enhancelinks/tests/base.py
src/collective/outputfilters/enhancelinks/tests/file.pdf
src/collective/outputfilters/enhancelinks/tests/file_csv.csv
src/collective/outputfilters/enhancelinks/tests/image.jpg
src/collective/outputfilters/enhancelinks/tests/test_adapter.py
src/collective/outputfilters/enhancelinks/tests/test_filter.py